magnethub/__init__.py
magnethub/loss.py
magnethub/paderborn.py
magnethub/sydney.py
magnethub/models/paderborn/cnn_3C90_experiment_1b4d8_model_f3915868_seed_0_fold_0.pt
magnethub/models/paderborn/cnn_3C92_experiment_ea1fe_model_72510647_seed_0_fold_0.pt
magnethub/models/paderborn/cnn_3C94_experiment_56441_model_55693612_seed_0_fold_0.pt
magnethub/models/paderborn/cnn_3C95_experiment_ad6ec_model_046383a5_seed_0_fold_0.pt
magnethub/models/paderborn/cnn_3E6_experiment_a7817_model_a1035e58_seed_0_fold_0.pt
magnethub/models/paderborn/cnn_3F4_experiment_c234d_model_2d43b97d_seed_0_fold_0.pt
magnethub/models/paderborn/cnn_77_experiment_268ae_model_5b7c92ed_seed_0_fold_0.pt
magnethub/models/paderborn/cnn_78_experiment_e5297_model_77fbd758_seed_0_fold_0.pt
magnethub/models/paderborn/cnn_79_experiment_45989_model_7227af72_seed_0_fold_0.pt
magnethub/models/paderborn/cnn_A_experiment_c9cfe_model_d893c778_p.pt
magnethub/models/paderborn/cnn_B_experiment_c9cfe_model_b6a920cc_p.pt
magnethub/models/paderborn/cnn_C_experiment_c9cfe_model_c1ced7b6_p.pt
magnethub/models/paderborn/cnn_D_experiment_c9cfe_model_11672810_p.pt
magnethub/models/paderborn/cnn_E_experiment_c9cfe_model_5ae50f9e_p.pt
magnethub/models/paderborn/cnn_ML95S_experiment_1c978_model_883a5d2f_seed_0_fold_0.pt
magnethub/models/paderborn/cnn_N27_experiment_8b7f0_model_20954a2a_seed_0_fold_0.pt
magnethub/models/paderborn/cnn_N30_experiment_5a78c_model_6bd86623_seed_0_fold_0.pt
magnethub/models/paderborn/cnn_N49_experiment_27442_model_d6234a32_seed_0_fold_0.pt
magnethub/models/paderborn/cnn_N87_experiment_985cb_model_d51b0f7e_seed_0_fold_0.pt
magnethub/models/paderborn/cnn_T37_experiment_a084a_model_fb31325e_seed_0_fold_0.pt
magnethub/models/sydney/3C90.pt
magnethub/models/sydney/3C92.pt
magnethub/models/sydney/3C94.pt
magnethub/models/sydney/3C95.pt
magnethub/models/sydney/3E6.pt
magnethub/models/sydney/3F4.pt
magnethub/models/sydney/77.pt
magnethub/models/sydney/78.pt
magnethub/models/sydney/79.pt
mag_net_hub-0.0.11.dist-info/METADATA
mag_net_hub-0.0.11.dist-info/WHEEL
mag_net_hub-0.0.11.dist-info/licenses/LICENSE
mag_net_hub-0.0.11.dist-info/RECORD
