Metadata-Version: 2.3
Name: mag-net-hub
Version: 0.0.11
Summary: MagNet Toolkit - Certified Models of the MagNet Challenge
Project-URL: Homepage, https://github.com/upb-lea/mag-net-hub
Project-URL: Issues, https://github.com/upb-lea/mag-net-hub/issues
Author: Wilhelm Kirchgässner
License-File: LICENSE
Classifier: License :: OSI Approved :: MIT License
Classifier: Operating System :: OS Independent
Classifier: Programming Language :: Python :: 3
Requires-Python: ~=3.10
Requires-Dist: joblib>=1.3.2
Requires-Dist: pandas>=2
Requires-Dist: scipy
Requires-Dist: torch>=2.0.1
Requires-Dist: torchinfo>=1.8.0
Requires-Dist: tqdm
